latex_ocr_server/__about__.py
latex_ocr_server/__init__.py
latex_ocr_server/__main__.py
latex_ocr_server/parse_args.py
latex_ocr_server/server.py
latex_ocr_server/nougat_latex_ocr/.git
latex_ocr_server/nougat_latex_ocr/.gitignore
latex_ocr_server/nougat_latex_ocr/LICENSE
latex_ocr_server/nougat_latex_ocr/README.md
latex_ocr_server/nougat_latex_ocr/all_requirements.txt
latex_ocr_server/nougat_latex_ocr/asset/img2latex.jpeg
latex_ocr_server/nougat_latex_ocr/base/__init__.py
latex_ocr_server/nougat_latex_ocr/base/common_util.py
latex_ocr_server/nougat_latex_ocr/base/driver.py
latex_ocr_server/nougat_latex_ocr/base/torch_utils/__init__.py
latex_ocr_server/nougat_latex_ocr/base/torch_utils/dl_util.py
latex_ocr_server/nougat_latex_ocr/base/torch_utils/scheduler_util.py
latex_ocr_server/nougat_latex_ocr/base/torch_utils/torch_util.py
latex_ocr_server/nougat_latex_ocr/config/base.yaml
latex_ocr_server/nougat_latex_ocr/examples/run_latex_ocr.py
latex_ocr_server/nougat_latex_ocr/examples/test_data/eq1.png
latex_ocr_server/nougat_latex_ocr/examples/test_data/eq2.png
latex_ocr_server/nougat_latex_ocr/examples/test_data/eq3.png
latex_ocr_server/nougat_latex_ocr/experiment/__init__.py
latex_ocr_server/nougat_latex_ocr/experiment/base_experiment.py
latex_ocr_server/nougat_latex_ocr/experiment/donut_experiment.py
latex_ocr_server/nougat_latex_ocr/metrics/__init__.py
latex_ocr_server/nougat_latex_ocr/metrics/meter.py
latex_ocr_server/nougat_latex_ocr/metrics/token_acc_metrics.py
latex_ocr_server/nougat_latex_ocr/mydatasets/__init__.py
latex_ocr_server/nougat_latex_ocr/mydatasets/base_datasets.py
latex_ocr_server/nougat_latex_ocr/mydatasets/donut_dataset.py
latex_ocr_server/nougat_latex_ocr/nougat_latex/__init__.py
latex_ocr_server/nougat_latex_ocr/nougat_latex/image_processing_nougat.py
latex_ocr_server/nougat_latex_ocr/nougat_latex/image_processor_img2latex.py
latex_ocr_server/nougat_latex_ocr/nougat_latex/util.py
latex_ocr_server/nougat_latex_ocr/tools/train_experiment.py
latex_ocr_server-0.1.2.dist-info/METADATA
latex_ocr_server-0.1.2.dist-info/WHEEL
latex_ocr_server-0.1.2.dist-info/RECORD
