Metadata-Version: 2.4
Name: latex-ocr-server
Version: 0.1.2
Summary: Turn image files into LaTeX equations with protocol buffers
Project-URL: Documentation, https://github.com/lucasvanmol/latex-ocr-server#readme
Project-URL: Issues, https://github.com/lucasvanmol/latex-ocr-server/issues
Project-URL: Source, https://github.com/lucasvanmol/latex-ocr-server
Author: Lucas Van Mol
License-Expression: MIT
Classifier: Development Status :: 4 - Beta
Classifier: Programming Language :: Python
Classifier: Programming Language :: Python :: 3.7
Classifier: Programming Language :: Python :: 3.8
Classifier: Programming Language :: Python :: 3.9
Classifier: Programming Language :: Python :: 3.10
Classifier: Programming Language :: Python :: 3.11
Classifier: Programming Language :: Python :: 3.12
Classifier: Programming Language :: Python :: Implementation :: CPython
Classifier: Programming Language :: Python :: Implementation :: PyPy
Requires-Python: >=3.7
Requires-Dist: google-api-python-client~=2.107.0
Requires-Dist: grpcio~=1.59.2
Requires-Dist: pillow~=10.1.0
Requires-Dist: torch~=2.1.0; python_version < '3.12'
Requires-Dist: torch~=2.2; python_version >= '3.12'
Requires-Dist: transformers~=4.35.1
